travis_cargo.py
travis_cargo-0.1.15.dist-info/DESCRIPTION.rst
travis_cargo-0.1.15.dist-info/METADATA
travis_cargo-0.1.15.dist-info/RECORD
travis_cargo-0.1.15.dist-info/WHEEL
travis_cargo-0.1.15.dist-info/entry_points.txt
travis_cargo-0.1.15.dist-info/metadata.json
travis_cargo-0.1.15.dist-info/top_level.txt
