Metadata-Version: 2.0
Name: travis-cargo
Version: 0.1.15
Summary: Manages interactions between travis and cargo/rust compilers.
Home-page: https://github.com/huonw/travis-cargo
Author: Huon Wilson
Author-email: dbau.pp@gmail.com
License: UNKNOWN
Download-URL: https://github.com/huonw/travis-cargo/tarball/0.1.15
Keywords: testing,travis,rust,cargo
Platform: UNKNOWN
Classifier: License :: OSI Approved :: Apache Software License
Classifier: License :: OSI Approved :: MIT License
Classifier: Topic :: Software Development :: Testing
Classifier: Programming Language :: Other
